README.txt
setup.cfg
setup.py
collective/__init__.py
collective.addtofolder.egg-info/PKG-INFO
collective.addtofolder.egg-info/SOURCES.txt
collective.addtofolder.egg-info/dependency_links.txt
collective.addtofolder.egg-info/entry_points.txt
collective.addtofolder.egg-info/namespace_packages.txt
collective.addtofolder.egg-info/not-zip-safe
collective.addtofolder.egg-info/paster_plugins.txt
collective.addtofolder.egg-info/requires.txt
collective.addtofolder.egg-info/top_level.txt
collective/addtofolder/__init__.py
collective/addtofolder/configlet.py
collective/addtofolder/configure.zcml
collective/addtofolder/interfaces.py
collective/addtofolder/patch.py
collective/addtofolder/setuphandlers.py
collective/addtofolder/tests.py
collective/addtofolder/browser/__init__.py
collective/addtofolder/browser/config.py
collective/addtofolder/browser/configure.zcml
collective/addtofolder/profiles/default/actionicons.xml
collective/addtofolder/profiles/default/addtofolder_marker.txt
collective/addtofolder/profiles/default/controlpanel.xml
collective/addtofolder/profiles/default/metadata.xml
docs/CONTRIBUTORS.txt
docs/HISTORY.txt
docs/INSTALL.txt
docs/LICENSE.GPL
docs/LICENSE.txt