Metadata-Version: 1.0
Name: collective.addtofolder
Version: 0.2
Summary: Add 'Add to parent folder' option. Allows users to add content to the folder you are currently in.
Home-page: http://dev.plone.org/collective/browser/collective.addtofolder
Author: Philip Bauer
Author-email: bauer@starzel.de
License: GPL
Platform: UNKNOWN
Classifier: Framework :: Plone
Classifier: Programming Language :: Python
Classifier: Topic :: Software Development :: Libraries :: Python Modules
